nwb_web_gui/__init__.py
nwb_web_gui/cmd_line.py
nwb_web_gui/config.py
nwb_web_gui/routes.py
nwb_web_gui/dashapps/__init__.py
nwb_web_gui/dashapps/components/__init__.py
nwb_web_gui/dashapps/components/navbar.py
nwb_web_gui/dashapps/pages/__init__.py
nwb_web_gui/dashapps/pages/converter/__init__.py
nwb_web_gui/dashapps/pages/converter/converter.py
nwb_web_gui/dashapps/pages/converter/init_coverter.py
nwb_web_gui/dashapps/pages/converter/converter_utils/__init__.py
nwb_web_gui/dashapps/pages/converter/converter_utils/converter_example.py
nwb_web_gui/dashapps/pages/converter/example_schemas/metadata_example.json
nwb_web_gui/dashapps/pages/converter/example_schemas/metadata_example.yaml
nwb_web_gui/dashapps/pages/converter/example_schemas/schema_conversion_example.json
nwb_web_gui/dashapps/pages/converter/example_schemas/schema_metadata.json
nwb_web_gui/dashapps/pages/converter/example_schemas/schema_source.json
nwb_web_gui/dashapps/pages/converter/example_schemas/source_example.json
nwb_web_gui/dashapps/pages/dashboard/__init__.py
nwb_web_gui/dashapps/pages/dashboard/init_dashboard.py
nwb_web_gui/dashapps/pages/viewer/__init__.py
nwb_web_gui/dashapps/pages/viewer/init_viewer.py
nwb_web_gui/dashapps/pages/viewer/viewer.py
nwb_web_gui/static/logo_nwb.png
nwb_web_gui/static/logo_nwb_square.png
nwb_web_gui/static/stylesheet.css
nwb_web_gui/templates/base.html
nwb_web_gui/templates/home.html
nwb_web_gui/templates/navbar.html
nwb_web_gui-0.1.6.dist-info/METADATA
nwb_web_gui-0.1.6.dist-info/WHEEL
nwb_web_gui-0.1.6.dist-info/entry_points.txt
nwb_web_gui-0.1.6.dist-info/top_level.txt
nwb_web_gui-0.1.6.dist-info/RECORD
