Metadata-Version: 2.1
Name: nwb-web-gui
Version: 0.1.6
Summary: Web graphical user interface for NWB conversion and exploring
Home-page: https://github.com/catalystneuro/nwb-web-gui
Author: Luiz Tauffer and Vinicius Camozzato Vaz
Author-email: luiz@taufferconsulting.com
License: UNKNOWN
Keywords: nwb
Platform: UNKNOWN
Requires-Dist: pynwb
Requires-Dist: nwb-conversion-tools
Requires-Dist: nwbwidgets
Requires-Dist: dash
Requires-Dist: dash-daq
Requires-Dist: dash-bootstrap-components
Requires-Dist: dash-cool-components
Requires-Dist: psutil
Requires-Dist: voila
Requires-Dist: pandas
Requires-Dist: jupyter
Requires-Dist: jupyter-client
Requires-Dist: json-schema-to-dash-forms
